odoo/addons/shopinvader_api_security_sale/README.rst
odoo/addons/shopinvader_api_security_sale/__init__.py
odoo/addons/shopinvader_api_security_sale/__manifest__.py
odoo/addons/shopinvader_api_security_sale/i18n/shopinvader_api_security_sale.pot
odoo/addons/shopinvader_api_security_sale/readme/CONTRIBUTORS.rst
odoo/addons/shopinvader_api_security_sale/readme/DESCRIPTION.rst
odoo/addons/shopinvader_api_security_sale/security/acl_product_product.xml
odoo/addons/shopinvader_api_security_sale/security/acl_product_template.xml
odoo/addons/shopinvader_api_security_sale/security/acl_uom_uom.xml
odoo/addons/shopinvader_api_security_sale/security/groups.xml
odoo/addons/shopinvader_api_security_sale/security/rule+acl_sale_order.xml
odoo/addons/shopinvader_api_security_sale/security/rule+acl_sale_order_line.xml
odoo/addons/shopinvader_api_security_sale/static/description/index.html
odoo_addon_shopinvader_api_security_sale-16.0.1.1.1.dist-info/METADATA
odoo_addon_shopinvader_api_security_sale-16.0.1.1.1.dist-info/WHEEL
odoo_addon_shopinvader_api_security_sale-16.0.1.1.1.dist-info/top_level.txt
odoo_addon_shopinvader_api_security_sale-16.0.1.1.1.dist-info/RECORD
